{
    "_id": 38144095,
    "game_name": "CS2",
    "match_name": "paiN - VS - Na`Vi",
    "tournament_short_name": "ESL Pro League",
    "start_time": "2025-03-09 17:30:00",
    "status": "live",
    "round": "bo3",
    "teams": [
        "paiN",
        "Na`Vi"
    ],
    "odds": [
        {
            "Date time": "09/03/2025 19:16:32",
            "Winner": {
                "paiN": "8.50",
                "Na`Vi": "1.05"
            },
            "Map 1": {
                "Na`Vi": "1.08",
                "paiN": "6.94"
            },
            "Map 2": {
                "Na`Vi": "1.20",
                "paiN": "4.23"
            }
        }
    ]
}